{ 
    "RoomType" : {
        "1" : { 
            "ID" : 1,
            "gameID" : 101,
            "Name" : "初级房",
            "BaseScore" : 100,
            "limit" : 100,
            "upperlimit1" : 240,
            "upperlimit2" : 0
        },
        "2" : { 
            "ID" : 2,
            "gameID" : 101,
            "Name" : "中级房",
            "BaseScore" : 1000,
            "limit" : 10000,
            "upperlimit1" : 240,
            "upperlimit2" : 0
        },
        "3" : { 
            "ID" : 3,
            "gameID" : 101,
            "Name" : "高级房",
            "BaseScore" : 10000,
            "limit" : 100000,
            "upperlimit1" : 240,
            "upperlimit2" : 0
        }
    },

    "Game" : {
        "101" : { 
            "ID" : 101,
            "type" : 1,
            "Name1" : "斗地主",
            "open" : 1,
            "Chinese" : 1,
            "English" : 0,
            "dllname" : "hlddz",
            "GameNum" : [8, 16],
            "HallCost" : [1002, 4, 1002, 8],
            "set1" : [120, 240],
            "set2" : [],
            "set3" : []
        },
        "102" : { 
            "ID" : 102,
            "type" : 1,
            "Name1" : "德州扑克",
            "open" : 0,
            "Chinese" : 0,
            "English" : 1,
            "dllname" : "",
            "GameNum" : [],
            "HallCost" : [],
            "set1" : [],
            "set2" : [],
            "set3" : []
        },
        "201" : { 
            "ID" : 201,
            "type" : 1,
            "Name1" : "炸金花",
            "open" : 0,
            "Chinese" : 1,
            "English" : 1,
            "dllname" : "",
            "GameNum" : [],
            "HallCost" : [],
            "set1" : [],
            "set2" : [],
            "set3" : []
        },
        "301" : { 
            "ID" : 301,
            "type" : 2,
            "Name1" : "四川麻将",
            "open" : 0,
            "Chinese" : 1,
            "English" : 0,
            "dllname" : "",
            "GameNum" : [],
            "HallCost" : [],
            "set1" : [],
            "set2" : [],
            "set3" : []
        },
        "401" : { 
            "ID" : 401,
            "type" : 2,
            "Name1" : "广州麻将",
            "open" : 0,
            "Chinese" : 0,
            "English" : 0,
            "dllname" : "",
            "GameNum" : [],
            "HallCost" : [],
            "set1" : [],
            "set2" : [],
            "set3" : []
        },
        "501" : { 
            "ID" : 501,
            "type" : 3,
            "Name1" : "四国军棋",
            "open" : 0,
            "Chinese" : 1,
            "English" : 0,
            "dllname" : "",
            "GameNum" : [],
            "HallCost" : [],
            "set1" : [],
            "set2" : [],
            "set3" : []
        },
        "502" : { 
            "ID" : 502,
            "type" : 3,
            "Name1" : "象棋",
            "open" : 0,
            "Chinese" : 1,
            "English" : 0,
            "dllname" : "",
            "GameNum" : [],
            "HallCost" : [],
            "set1" : [],
            "set2" : [],
            "set3" : []
        }
    },

    "Role" : {
        "1" : { 
            "ID" : 1,
            "icon" : "",
            "picture" : "face_1"
        },
        "2" : { 
            "ID" : 2,
            "icon" : "",
            "picture" : "face_2"
        },
        "3" : { 
            "ID" : 3,
            "icon" : "",
            "picture" : "face_3"
        }
    },

    "Parameter" : {
        "1" : { 
            "ID" : 1,
            "para" : 50
        }
    }
}